mach/__init__.py
mach/__version__.py
mach/build.py
mach/cache.py
mach/commands.py
mach/exceptions.py
mach/git.py
mach/parse.py
mach/terraform.py
mach/updater.py
mach/utils.py
mach/validate.py
mach/variables.py
mach/yaml.py
mach/bootstrap/__init__.py
mach/bootstrap/component.py
mach/bootstrap/config.py
mach/templates/__init__.py
mach/templates/site.tf
mach/templates/partials/amplience.tf
mach/templates/partials/aws.tf
mach/templates/partials/azure.tf
mach/templates/partials/azure_app_service_plans.tf
mach/templates/partials/commercetools.tf
mach/templates/partials/commercetools_frontend.tf
mach/templates/partials/component.tf
mach/templates/partials/component_aws_variables.tf
mach/templates/partials/component_azure_variables.tf
mach/templates/partials/components.tf
mach/templates/partials/contentful.tf
mach/templates/partials/stores.tf
mach/templates/partials/endpoints/aws_endpoints.tf
mach/templates/partials/endpoints/aws_url_locals.tf
mach/templates/partials/endpoints/azure_frontdoor.tf
mach/templates/partials/endpoints/azure_frontdoor_endpoint.tf
mach/templates/partials/endpoints/azure_url_locals.tf
mach/types/__init__.py
mach/types/base.py
mach/types/components.py
mach/types/fields.py
mach/types/general_config.py
mach/types/mach.py
mach/types/shared.py
mach/types/sites.py
mach/types/values.py
mach_composer-1.2.4.dist-info/LICENSE
mach_composer-1.2.4.dist-info/METADATA
mach_composer-1.2.4.dist-info/WHEEL
mach_composer-1.2.4.dist-info/entry_points.txt
mach_composer-1.2.4.dist-info/top_level.txt
mach_composer-1.2.4.dist-info/RECORD
