Metadata-Version: 2.1
Name: mach-composer
Version: 1.2.4
Summary: MACH composer
Home-page: https://github.com/labd/mach-composer
Author: Lab Digital B.V.
Author-email: info@labdigital.nl
License: MIT
Project-URL: Documentation, https://docs.machcomposer.io
Project-URL: Source, https://github.com/labd/mach-composer
Platform: UNKNOWN
Classifier: Development Status :: 5 - Production/Stable
Classifier: License :: OSI Approved :: MIT License
Classifier: Programming Language :: Python :: 3
Classifier: Programming Language :: Python :: 3.8
Classifier: Programming Language :: Python :: Implementation :: CPython
License-File: LICENSE
Requires-Dist: arrow (==1.2.2)
Requires-Dist: attrs (==21.4.0)
Requires-Dist: binaryornot (==0.4.4)
Requires-Dist: certifi (==2021.10.8)
Requires-Dist: chardet (==4.0.0)
Requires-Dist: charset-normalizer (==2.0.12)
Requires-Dist: click (==8.0.4)
Requires-Dist: colorama (==0.4.4)
Requires-Dist: cookiecutter (==1.7.3)
Requires-Dist: dataclasses-json (==0.5.6)
Requires-Dist: dataclasses-jsonschema (==2.15.0)
Requires-Dist: filelock (==3.6.0)
Requires-Dist: idna (==3.3)
Requires-Dist: importlib-metadata (==4.11.2)
Requires-Dist: importlib-resources (==5.4.0)
Requires-Dist: jinja2 (==3.0.3)
Requires-Dist: jinja2-time (==0.2.0)
Requires-Dist: jsonschema (==4.4.0)
Requires-Dist: markupsafe (==2.1.0)
Requires-Dist: marshmallow (==3.14.1)
Requires-Dist: marshmallow-enum (==1.5.1)
Requires-Dist: mypy-extensions (==0.4.3)
Requires-Dist: poyo (==0.5.0)
Requires-Dist: pyrsistent (==0.18.1)
Requires-Dist: python-dateutil (==2.8.2)
Requires-Dist: python-slugify (==6.1.1)
Requires-Dist: pyyaml (==5.4.1)
Requires-Dist: pyyaml-include (==1.2.post2)
Requires-Dist: requests (==2.27.1)
Requires-Dist: requests-file (==1.5.1)
Requires-Dist: six (==1.16.0)
Requires-Dist: text-unidecode (==1.3)
Requires-Dist: tldextract (==3.2.0)
Requires-Dist: typing-extensions (==4.1.1)
Requires-Dist: typing-inspect (==0.7.1)
Requires-Dist: urllib3 (==1.26.8)
Requires-Dist: zipp (==3.7.0)
